proxigraph/__init__.py
proxigraph/config.py
proxigraph/core.py
proxigraph/example.py
proxigraph/graphs.py
proxigraph/plot.py
proxigraph/points.py
proxigraph/utils.py
ProxiGraph-0.1.2.dist-info/METADATA
ProxiGraph-0.1.2.dist-info/WHEEL
ProxiGraph-0.1.2.dist-info/top_level.txt
ProxiGraph-0.1.2.dist-info/RECORD
